pyd_tpl/README.md
pyd_tpl/__init__.py
pyd_tpl/pyd_tpl.py
pyd_tpl/setup.tpl
pyd_tpl/py2/class.tpl
pyd_tpl/py2/demo.tpl
pyd_tpl/py2/pyd_tool.tpl
pyd_tpl/py3/class.tpl
pyd_tpl/py3/demo.tpl
pyd_tpl/py3/pyd_tool.tpl
pyd_tpl-0.1.3.data/data/pyd_tpl/setup.tpl
pyd_tpl-0.1.3.data/data/pyd_tpl/py2/class.tpl
pyd_tpl-0.1.3.data/data/pyd_tpl/py2/demo.tpl
pyd_tpl-0.1.3.data/data/pyd_tpl/py2/pyd_tool.tpl
pyd_tpl-0.1.3.data/data/pyd_tpl/py3/class.tpl
pyd_tpl-0.1.3.data/data/pyd_tpl/py3/demo.tpl
pyd_tpl-0.1.3.data/data/pyd_tpl/py3/pyd_tool.tpl
pyd_tpl-0.1.3.dist-info/METADATA
pyd_tpl-0.1.3.dist-info/WHEEL
pyd_tpl-0.1.3.dist-info/entry_points.txt
pyd_tpl-0.1.3.dist-info/top_level.txt
pyd_tpl-0.1.3.dist-info/RECORD
