Metadata-Version: 2.1
Name: pyd-tpl
Version: 0.1.3
Summary: pyd generate tools
Home-page: https://github.com/yafeile/pyd_tpl
Author: Cat
License: UNKNOWN
Keywords: pyd generate,pyd templates
Platform: any
Requires-Dist: Jinja2 (>=2.11.2)
